eventrabbit/__init__.py
eventrabbit/common.py
eventrabbit/connection.py
eventrabbit/context.py
eventrabbit/decorators.py
eventrabbit/exceptions.py
eventrabbit/interface.py
eventrabbit/logger.py
eventrabbit/model.py
eventrabbit/queue.py
eventrabbit/queue_runtime.py
eventrabbit-0.1.1.dist-info/METADATA
eventrabbit-0.1.1.dist-info/WHEEL
eventrabbit-0.1.1.dist-info/RECORD
