Metadata-Version: 2.1
Name: eventrabbit
Version: 0.1.1
Summary: Event sourcing library for RabbitMQ (aio_pika)
Home-page: https://your-homepage-url.com
License: MIT
Author: Artem
Author-email: artemsenkevic348@gmail.com
Requires-Python: >=3.11,<4.0
Classifier: License :: OSI Approved :: MIT License
Classifier: Programming Language :: Python :: 3
Classifier: Programming Language :: Python :: 3.11
Classifier: Programming Language :: Python :: 3.12
Classifier: Programming Language :: Python :: 3.13
Requires-Dist: aio_pika (>=9.0.0)
Requires-Dist: pydantic (>=2.0.0,<3.0.0)
